{"title": "국내여행", "item_list": [{"productId": 100000013039, "productName": "[경주] 버드파크 입장권 ", "productPrice": 8000, "productImage": "https://static.coupangcdn.com/image/travel_reactor/product/content/vendorItemPackage/2016/12/14/3013766502/07fb1ccf-1e18-4f8a-b1a1-b58505b5c1b0.jpg", "productUrl": "https://coupa.ng/b27MuC", "categoryName": "국내여행", "keyword": "국내여행", "rank": 1, "isRocket": false, "isFreeShipping": false}, {"productId": 100000012960, "productName": "[제주] 서귀포잠수함", "productPrice": 39000, "productImage": "https://static.coupangcdn.com/image/travel_reactor/travelSeller/common/A00186691/453ac989-dfeb-472c-b34a-b6c55969b4fc.jpg", "productUrl": "https://coupa.ng/b27MuD", "categoryName": "국내여행", "keyword": "국내여행", "rank": 2, "isRocket": false, "isFreeShipping": false}, {"productId": 30000000547354, "productName": "[강원/인제] [7/17(토),8/7(토) 出 확정] 천상의 화원 '곰배령' (당일)(1인 2좌석 제공)", "productPrice": 53000, "productImage": "https://static.coupangcdn.com/image/travel_reactor/travelSeller/common/A00176900/8e0e5f8a-3880-41aa-a53b-e94ce4b7c147.jpg", "productUrl": "https://coupa.ng/b27MuE", "categoryName": "국내여행", "keyword": "국내여행", "rank": 3, "isRocket": false, "isFreeShipping": false}, {"productId": 30000000547816, "productName": "[강원/평창] 청옥산 육백마지기 (당일) (일반 트레킹 코스)", "productPrice": 45000, "productImage": "https://static.coupangcdn.com/image/travel_reactor/travelSeller/common/A00176900/8535cd57-fff7-4c15-8d54-9f3a3455bfe4.jpg", "productUrl": "https://coupa.ng/b27MuF", "categoryName": "국내여행", "keyword": "국내여행", "rank": 4, "isRocket": false, "isFreeShipping": false}, {"productId": 100000012974, "productName": "[제주] 레일바이크", "productPrice": 9800, "productImage": "https://static.coupangcdn.com/image/travel_reactor/travelSeller/common/A00186691/9d5b9ca9-7dfb-44e3-a99e-b2a587abb125.jpg", "productUrl": "https://coupa.ng/b27MuG", "categoryName": "국내여행", "keyword": "국내여행", "rank": 5, "isRocket": false, "isFreeShipping": false}, {"productId": 100000038096, "productName": "[제주] 퐁당해양레저 (투명카약/제트보트/스피드보트/제트스키)", "productPrice": 9900, "productImage": "https://static.coupangcdn.com/image/travel_reactor/travelSeller/common/A00186691/9c1d4e07-4ff2-4d50-903d-c79c93ca2044.jpg", "productUrl": "https://coupa.ng/b27MuI", "categoryName": "국내여행", "keyword": "국내여행", "rank": 6, "isRocket": false, "isFreeShipping": false}, {"productId": 100000012926, "productName": "[제주] 허브동산 (♥심쿵혜택♥)", "productPrice": 8000, "productImage": "https://static.coupangcdn.com/image/travel_reactor/travelSeller/common/A00186691/fb16194e-ebbb-48a4-aba9-513b7b6c3f70.jpg", "productUrl": "https://coupa.ng/b27MuJ", "categoryName": "국내여행", "keyword": "국내여행", "rank": 7, "isRocket": false, "isFreeShipping": false}, {"productId": 30000000538935, "productName": "[제주] 아쿠아플라넷+서귀포잠수함", "productPrice": 47000, "productImage": "https://static.coupangcdn.com/image/travel_reactor/travelSeller/common/A00220576/3389121b-1514-413c-803e-b9d81a21b3fd.jpg", "productUrl": "https://coupa.ng/b27MuK", "categoryName": "국내여행", "keyword": "국내여행", "rank": 8, "isRocket": false, "isFreeShipping": false}, {"productId": 100000013619, "productName": "[부산] 부산아쿠아리움+영화체험박물관+트릭아이", "productPrice": 23500, "productImage": "https://static.coupangcdn.com/image/travel_reactor/travelSeller/common/A00186335/72a45c64-4596-4ddb-9a28-4d38ec49738d.jpg", "productUrl": "https://coupa.ng/b27MuL", "categoryName": "국내여행", "keyword": "국내여행", "rank": 9, "isRocket": false, "isFreeShipping": false}, {"productId": 30000000534408, "productName": "[포항시] 윈호텔", "productPrice": 59400, "productImage": "https://static.coupangcdn.com/image/travel_reactor/travelConnect/hotel/C00242129/b86fe553-18d7-4ad2-aa45-b20d2804fec2.jpg", "productUrl": "https://coupa.ng/b27MuM", "categoryName": "국내여행", "keyword": "국내여행", "rank": 10, "isRocket": false, "isFreeShipping": false}]}