{"title": "도서-음반-DVD", "item_list": [{"productId": 5717365944, "productName": "[시공주니어]와일드 심포니 (양장), 시공주니어, 댄 브라운", "productPrice": 13050, "productImage": "https://static.coupangcdn.com/image/retail-product-api/A00077021/58105401/64285134/main/9791165795863_L.jpg", "productUrl": "https://coupa.ng/b2xTQi", "categoryName": "도서/음반/DVD", "keyword": "도서/음반/DVD", "rank": 1, "isRocket": true, "isFreeShipping": false}, {"productId": 5676997675, "productName": "[단꿈아이]설민석의 세계사 대모험 9 : 중국 편 분열의 시작, 단꿈아이, 설민석", "productPrice": 10800, "productImage": "https://static.coupangcdn.com/image/retail-product-api/A00077021/57515083/63615992/main/9791191496017_L.jpg", "productUrl": "https://coupa.ng/b2xTQj", "categoryName": "도서/음반/DVD", "keyword": "도서/음반/DVD", "rank": 2, "isRocket": true, "isFreeShipping": false}, {"productId": 1762998328, "productName": "엄마랑 낱말카드 150장 세이펜 호환, 훈민출판사", "productPrice": 16500, "productImage": "https://static.coupangcdn.com/image/retail/images/335345303053167-d577be28-06da-4ac7-8e30-c1f7be1c0a50.png", "productUrl": "https://coupa.ng/b2xTQk", "categoryName": "도서/음반/DVD", "keyword": "도서/음반/DVD", "rank": 3, "isRocket": true, "isFreeShipping": false}, {"productId": 245656934, "productName": "집중력을 키워주는 픽셀아트 컬러링북 세트 전3권, 달리는곰셋", "productPrice": 16800, "productImage": "https://static.coupangcdn.com/image/retail/images/2019/06/25/10/3/a8f3b3fd-b8d0-4c92-9cab-56d6ba9393a4.jpg", "productUrl": "https://coupa.ng/b2xTQl", "categoryName": "도서/음반/DVD", "keyword": "도서/음반/DVD", "rank": 4, "isRocket": true, "isFreeShipping": false}, {"productId": 5580995790, "productName": "조국의 시간:아픔과 진실 말하지 못한 생각, 조국, 한길사", "productPrice": 15300, "productImage": "https://static.coupangcdn.com/image/vendor_inventory/319b/7bc0d2cc96ff4f66c3af41aedc06956a00446c3e0faf14b2dbe813e338e2.jpg", "productUrl": "https://coupa.ng/b2xTQn", "categoryName": "도서/음반/DVD", "keyword": "도서/음반/DVD", "rank": 5, "isRocket": true, "isFreeShipping": false}, {"productId": 2275142813, "productName": "어떻게 말해줘야 할까:오은영의 현실밀착 육아회화, 김영사", "productPrice": 15750, "productImage": "https://static.coupangcdn.com/image/vendor_inventory/17f6/453a8f332d1c9306bfee22fd58137e08da7851360571a69a4e374e8d37c7.jpg", "productUrl": "https://coupa.ng/b2xTQo", "categoryName": "도서/음반/DVD", "keyword": "도서/음반/DVD", "rank": 6, "isRocket": true, "isFreeShipping": false}, {"productId": 1356512239, "productName": "돌쟁이 스티커북 6권세트 아기동물 + 맛있는음식 + 인지놀이 + 자동차탈것 + 우리가족 + 창의놀이, 마이리틀타이거", "productPrice": 19800, "productImage": "https://static.coupangcdn.com/image/retail/images/2020/03/16/15/7/0c5d0cd0-5ec5-4d69-8409-5518e0182f24.jpg", "productUrl": "https://coupa.ng/b2xTQp", "categoryName": "도서/음반/DVD", "keyword": "도서/음반/DVD", "rank": 7, "isRocket": true, "isFreeShipping": false}, {"productId": 203569, "productName": "뽀로로 가방 스티커 놀이북: 탈것:붙였다 떼었다!, 키즈아이콘", "productPrice": 3600, "productImage": "https://static.coupangcdn.com/image/vendor_inventory/21c0/4340d29dd0b217f5c6dd990a2b9a4332eda598b3051e0eb44f7d2da9abf4.jpg", "productUrl": "https://coupa.ng/b2xTQq", "categoryName": "도서/음반/DVD", "keyword": "도서/음반/DVD", "rank": 8, "isRocket": true, "isFreeShipping": false}, {"productId": 202975551, "productName": "핑크퐁 가방 스티커 BEST 4종 세트 : 아기상어 스티커+동물 스티커+자동차 스티커+공룡 스티커, 스마트스터디", "productPrice": 16200, "productImage": "https://static.coupangcdn.com/image/product/image/vendoritem/2019/05/02/4557562364/0ca0a1c1-247f-44be-b495-730b4c648926.jpg", "productUrl": "https://coupa.ng/b2xTQr", "categoryName": "도서/음반/DVD", "keyword": "도서/음반/DVD", "rank": 9, "isRocket": true, "isFreeShipping": false}, {"productId": 4321074798, "productName": "뽀로로 머리가 좋아지는 만들기 우드락 탈것 + 종이 마을 만들기 + 2in1 보드놀이판 + 스티커 + 매직스티커 세트 + 크레용 12색, 키즈아이콘", "productPrice": 18900, "productImage": "https://static.coupangcdn.com/image/rs_quotation_api/612f/514e5f66deaf75298b8c165cb615250cb6a09873ba65ef2be41466c61da5.jpg", "productUrl": "https://coupa.ng/b2xTQs", "categoryName": "도서/음반/DVD", "keyword": "도서/음반/DVD", "rank": 10, "isRocket": true, "isFreeShipping": false}]}