{"title": "반려동물용품", "item_list": [{"productId": 2055461981, "productName": "굿데이 강아지간식 건강한 육포 300g, 오리가슴살 스틱, 1개", "productPrice": 10500, "productImage": "https://static.coupangcdn.com/image/product/image/vendoritem/2018/10/26/3707467639/2e1c4e46-4a76-4358-b2ee-3e660198456e.jpg", "productUrl": "https://link.coupang.com/a/hLoGe", "categoryName": "반려동물용품", "keyword": "반려동물용품", "rank": 1, "isRocket": true, "isFreeShipping": false}, {"productId": 4919736873, "productName": "탐사 고양이 사료 연어, 3kg, 1개", "productPrice": 13190, "productImage": "https://static.coupangcdn.com/image/retail/images/12286549635727-15386d6a-1b6e-4190-9ab7-717ad8af30ac.jpg", "productUrl": "https://link.coupang.com/a/hLoGf", "categoryName": "반려동물용품", "keyword": "반려동물용품", "rank": 2, "isRocket": true, "isFreeShipping": false}, {"productId": 1550850914, "productName": "라무달리 전연령 강아지 금동사료, 가수분해연어, 2kg, 1개", "productPrice": 14530, "productImage": "https://static.coupangcdn.com/image/retail/images/1021550008363905-8cf0b073-7080-42f8-aacc-e6a538788c35.jpg", "productUrl": "https://link.coupang.com/a/hLoGg", "categoryName": "반려동물용품", "keyword": "반려동물용품", "rank": 3, "isRocket": true, "isFreeShipping": false}, {"productId": 4541160509, "productName": "펫둥이 짜먹는 고양이 간식 3가지맛 30P, 참치, 연어, 닭고기, 1세트", "productPrice": 10300, "productImage": "https://static.coupangcdn.com/image/retail/images/84830880223984-e59ee3eb-5139-4b90-bfc5-8778888e3d8b.jpg", "productUrl": "https://link.coupang.com/a/hLoGh", "categoryName": "반려동물용품", "keyword": "반려동물용품", "rank": 4, "isRocket": true, "isFreeShipping": false}, {"productId": 67895672, "productName": "오랄클리닉 반려동물 치석제거용 덴탈껌 300g, 청사과, 1개", "productPrice": 8280, "productImage": "https://static.coupangcdn.com/image/retail/images/1127998950993932-28298217-72c6-454c-83d6-903bfc9e3550.jpg", "productUrl": "https://link.coupang.com/a/hLoGi", "categoryName": "반려동물용품", "keyword": "반려동물용품", "rank": 5, "isRocket": true, "isFreeShipping": false}, {"productId": 22849195, "productName": "네츄럴코어 전연령 에코플러스1 그레인프리 치킨&연어 건식사료, 닭, 7kg", "productPrice": 40900, "productImage": "https://static.coupangcdn.com/image/retail/images/6049189385555-ff2e1b22-8a09-4be5-89c3-06e42a5e100e.jpg", "productUrl": "https://link.coupang.com/a/hLoGj", "categoryName": "반려동물용품", "keyword": "반려동물용품", "rank": 6, "isRocket": true, "isFreeShipping": false}, {"productId": 29417806, "productName": "탐사 강아지 배변패드 일반형(53 x 43cm) 3단계 120매, 1개", "productPrice": 18990, "productImage": "https://static.coupangcdn.com/image/retail/images/157931820871764-476db356-b487-4ac7-a3f8-1f1028abf20e.jpg", "productUrl": "https://link.coupang.com/a/hLoGk", "categoryName": "반려동물용품", "keyword": "반려동물용품", "rank": 7, "isRocket": true, "isFreeShipping": false}, {"productId": 9859862, "productName": "프리미엄 로얄 고양이캔 콤보, 혼합 6종, 24개", "productPrice": 19490, "productImage": "https://static.coupangcdn.com/image/product/image/vendoritem/2019/02/14/3068758408/2ab7cee9-f47c-47fa-afee-e429c5f236e9.jpg", "productUrl": "https://link.coupang.com/a/hLoGl", "categoryName": "반려동물용품", "keyword": "반려동물용품", "rank": 8, "isRocket": true, "isFreeShipping": false}, {"productId": 9486986, "productName": "비스트로 고양이용 흰살참치와 닭안심 캔, 24개입, 160g", "productPrice": 20990, "productImage": "https://static.coupangcdn.com/image/retail/images/235796365707383-62401cec-141e-4cc4-af47-20cfd7ed1f10.jpg", "productUrl": "https://link.coupang.com/a/hLoGm", "categoryName": "반려동물용품", "keyword": "반려동물용품", "rank": 9, "isRocket": true, "isFreeShipping": false}, {"productId": 68523069, "productName": "탐사 강아지 배변패드 특대형(90 x 65cm) 흡수력 3단계 60매, 1개", "productPrice": 21840, "productImage": "https://static.coupangcdn.com/image/retail/images/161666683552990-90bc2568-ad24-4c30-9315-0d5d09e87199.jpg", "productUrl": "https://link.coupang.com/a/hLoGn", "categoryName": "반려동물용품", "keyword": "반려동물용품", "rank": 10, "isRocket": true, "isFreeShipping": false}]}