{"title": "뷰티", "item_list": [{"productId": 5380703499, "productName": "센카 퍼펙트 휩 클렌징 폼 리뉴얼, 120g, 2개", "productPrice": 9740, "productImage": "https://static.coupangcdn.com/image/retail/images/1374085883418856-bbe4344d-4080-495a-b38f-b7b661e7e728.jpg", "productUrl": "https://link.coupang.com/a/psHnE", "categoryName": "뷰티", "keyword": "뷰티", "rank": 1, "isRocket": true, "isFreeShipping": false}, {"productId": 1319773082, "productName": "폴메디슨 시그니처 대용량 퍼퓸 바디워시 화이트머스크향, 2개, 1077ml", "productPrice": 18570, "productImage": "https://static.coupangcdn.com/image/retail/images/72816344231646-68d38cca-6ea4-4bb5-ac7c-66599c2c190f.png", "productUrl": "https://link.coupang.com/a/psHnF", "categoryName": "뷰티", "keyword": "뷰티", "rank": 2, "isRocket": true, "isFreeShipping": false}, {"productId": 1266713, "productName": "케라시스 러블리 앤 로맨틱 퍼퓸샴푸 꽃향, 980ml, 3개", "productPrice": 14650, "productImage": "https://static.coupangcdn.com/image/retail/images/2020/03/20/0/0/1fb25151-4542-46b5-bf57-06a1ec5b717a.jpg", "productUrl": "https://link.coupang.com/a/psHnG", "categoryName": "뷰티", "keyword": "뷰티", "rank": 3, "isRocket": true, "isFreeShipping": false}, {"productId": 181699807, "productName": "밀크바오밥 바디워시 화이트머스크향, 1000ml, 1개", "productPrice": 12800, "productImage": "https://static.coupangcdn.com/image/retail/images/7093835784704304-49706c46-484c-45da-b2c0-1e5ed38b3a51.jpg", "productUrl": "https://link.coupang.com/a/psHnH", "categoryName": "뷰티", "keyword": "뷰티", "rank": 4, "isRocket": true, "isFreeShipping": false}, {"productId": 4932903828, "productName": "뉴트로지나 딥클린 포밍 클렌저, 100g, 3개", "productPrice": 12800, "productImage": "https://static.coupangcdn.com/image/retail/images/17202391318825029-d374c64f-b085-4545-9a5c-27c59d320a8b.jpeg", "productUrl": "https://link.coupang.com/a/psHnJ", "categoryName": "뷰티", "keyword": "뷰티", "rank": 5, "isRocket": true, "isFreeShipping": false}, {"productId": 158853778, "productName": "아모스 컬링 에센스 2X 헤어에센스, 150ml, 2개", "productPrice": 15460, "productImage": "https://static.coupangcdn.com/image/vendor_inventory/50d4/1d9c466f48b53ff6eb75a602e1e092496cf26795815d51f79233269b1051.jpg", "productUrl": "https://link.coupang.com/a/psHnK", "categoryName": "뷰티", "keyword": "뷰티", "rank": 6, "isRocket": false, "isFreeShipping": true}, {"productId": 4577732587, "productName": "이니스프리 화산송이 모공 클렌징 폼, 300g, 1개", "productPrice": 7810, "productImage": "https://static.coupangcdn.com/image/retail/images/276111687912643-90a8eb18-083e-40be-befe-15e2d6b171e6.jpg", "productUrl": "https://link.coupang.com/a/psHnL", "categoryName": "뷰티", "keyword": "뷰티", "rank": 7, "isRocket": true, "isFreeShipping": false}, {"productId": 1732481, "productName": "메디플라워 엠보싱 소프트 화장솜, 300매, 3개", "productPrice": 9900, "productImage": "https://static.coupangcdn.com/image/product/image/vendoritem/2019/02/19/3174580187/08c45687-4e55-4800-beed-7e5dc8d7767a.jpg", "productUrl": "https://link.coupang.com/a/psHnM", "categoryName": "뷰티", "keyword": "뷰티", "rank": 8, "isRocket": true, "isFreeShipping": false}, {"productId": 247911756, "productName": "다슈 매직 커버 니플밴드 52매, 2개", "productPrice": 11900, "productImage": "https://static.coupangcdn.com/image/retail/images/16332786936468403-556a5aa2-daa9-4051-87ea-ae1f587ed7ca.jpg", "productUrl": "https://link.coupang.com/a/psHnN", "categoryName": "뷰티", "keyword": "뷰티", "rank": 9, "isRocket": true, "isFreeShipping": false}, {"productId": 4583248357, "productName": "본트리 베리 에센스 선블럭 SPF50+ PA++++, 50ml, 2개", "productPrice": 12300, "productImage": "https://static.coupangcdn.com/image/retail/images/532402460541110-69117b46-bde5-4b90-b133-8c1609b65197.jpg", "productUrl": "https://link.coupang.com/a/psHnO", "categoryName": "뷰티", "keyword": "뷰티", "rank": 10, "isRocket": true, "isFreeShipping": false}]}