{"title": "식품", "item_list": [{"productId": 172073083, "productName": "수원축협 무항생제 인증 대란 30구, 1560g, 1개", "productPrice": 7990, "productImage": "https://static.coupangcdn.com/image/retail/images/2018/12/28/9/0/2706d072-91f8-40d1-b609-bac824deeeed.jpg", "productUrl": "https://link.coupang.com/a/i3QYp", "categoryName": "식품", "keyword": "식품", "rank": 1, "isRocket": true, "isFreeShipping": false}, {"productId": 4708084849, "productName": "매일우유 오리지널 멸균, 200ml, 24팩", "productPrice": 14080, "productImage": "https://static.coupangcdn.com/image/retail/images/865733839734639-a7d95a75-dd71-4a53-8aa0-8de0f864cf09.jpg", "productUrl": "https://link.coupang.com/a/i3QYq", "categoryName": "식품", "keyword": "식품", "rank": 2, "isRocket": true, "isFreeShipping": false}, {"productId": 1524568260, "productName": "무항생제 인증 아침에 대란 30구, 1560g, 1개", "productPrice": 8080, "productImage": "https://static.coupangcdn.com/image/retail/images/4838127527856110-36ea3855-1d36-425b-bed2-477761bd88f5.jpg", "productUrl": "https://link.coupang.com/a/i3QYr", "categoryName": "식품", "keyword": "식품", "rank": 3, "isRocket": true, "isFreeShipping": false}, {"productId": 1074470750, "productName": "곰곰 국내산 감자, 2kg", "productPrice": 6770, "productImage": "https://static.coupangcdn.com/image/retail/images/5577606994565-c1b098c4-e907-4171-bfae-b38a773c75cc.jpg", "productUrl": "https://link.coupang.com/a/i3QYs", "categoryName": "식품", "keyword": "식품", "rank": 4, "isRocket": true, "isFreeShipping": false}, {"productId": 1308889924, "productName": "곰곰 슈레드 모짜렐라 피자치즈, 1kg, 1개", "productPrice": 9700, "productImage": "https://static.coupangcdn.com/image/retail/images/82989828437051-13f73e44-c6cb-4b62-97c4-a5fb595d0811.jpg", "productUrl": "https://link.coupang.com/a/i3QYt", "categoryName": "식품", "keyword": "식품", "rank": 5, "isRocket": true, "isFreeShipping": false}, {"productId": 323576607, "productName": "곰곰 맛있는 밤고구마, 1.5kg, 1박스", "productPrice": 7470, "productImage": "https://static.coupangcdn.com/image/retail/images/254974176857878-b0cd5c48-46fe-40af-a5f6-3823aae84691.jpg", "productUrl": "https://link.coupang.com/a/i3QYu", "categoryName": "식품", "keyword": "식품", "rank": 6, "isRocket": true, "isFreeShipping": false}, {"productId": 119465439, "productName": "상하목장 유기농 우유, 24팩, 200ml", "productPrice": 21160, "productImage": "https://static.coupangcdn.com/image/product/image/vendoritem/2018/10/08/3000244423/516b34f6-8aba-4b38-9787-619a4b02f9ad.jpg", "productUrl": "https://link.coupang.com/a/i3QYv", "categoryName": "식품", "keyword": "식품", "rank": 7, "isRocket": true, "isFreeShipping": false}, {"productId": 319152577, "productName": "칠성사이다, 30개입, 210ml", "productPrice": 14250, "productImage": "https://static.coupangcdn.com/image/retail/images/16568343642030-a67fb8c7-5361-41ec-a89a-ecf54d550407.jpg", "productUrl": "https://link.coupang.com/a/i3QYw", "categoryName": "식품", "keyword": "식품", "rank": 8, "isRocket": true, "isFreeShipping": false}, {"productId": 156688977, "productName": "다향오리 1등급 훈제 오리 슬라이스, 600g, 1개", "productPrice": 11760, "productImage": "https://static.coupangcdn.com/image/retail/images/107202630603864-9300fd85-73c5-45bf-9bcf-83ee1a15a28d.jpg", "productUrl": "https://link.coupang.com/a/i3QYx", "categoryName": "식품", "keyword": "식품", "rank": 9, "isRocket": true, "isFreeShipping": false}, {"productId": 1473796614, "productName": "곰곰 호주산 소고기 앞다리살 국거리용 300g (냉장), 1개", "productPrice": 9390, "productImage": "https://static.coupangcdn.com/image/retail/images/7789812867576679-b9c97692-d200-4bc3-b701-9159865eff58.jpg", "productUrl": "https://link.coupang.com/a/i3QYy", "categoryName": "식품", "keyword": "식품", "rank": 10, "isRocket": true, "isFreeShipping": false}]}