{"title": "완구-취미", "item_list": [{"productId": 1582685139, "productName": "탐사 스케치북 도화지 130g 8절, 250매", "productPrice": 9570, "productImage": "https://static.coupangcdn.com/image/retail/images/112631106525777-0f31b84d-b51b-45bb-9075-8946c66c86c3.jpg", "productUrl": "https://coupa.ng/b4bieR", "categoryName": "완구/취미", "keyword": "완구/취미", "rank": 1, "isRocket": true, "isFreeShipping": false}, {"productId": 1418532020, "productName": "키즈팡팡 알록달록 바다어부 자석 낚시놀이 67p, 혼합색상", "productPrice": 15610, "productImage": "https://static.coupangcdn.com/image/retail/images/67282104914762-f68d3b8d-77ba-4da4-b073-ed61c62046e3.jpg", "productUrl": "https://coupa.ng/b4bieS", "categoryName": "완구/취미", "keyword": "완구/취미", "rank": 2, "isRocket": true, "isFreeShipping": false}, {"productId": 1460362707, "productName": "플레이도우 뉴 크리에이티브 센터 완구세트, 혼합색상, 2245g", "productPrice": 36330, "productImage": "https://static.coupangcdn.com/image/retail/images/2020/04/10/19/1/630112af-abaf-46d0-8eb3-501decdf552e.jpg", "productUrl": "https://coupa.ng/b4bieU", "categoryName": "완구/취미", "keyword": "완구/취미", "rank": 3, "isRocket": true, "isFreeShipping": false}, {"productId": 1676161965, "productName": "닌샵 디지털 주방 저울, 혼합색상", "productPrice": 8070, "productImage": "https://static.coupangcdn.com/image/retail/images/2020/06/21/11/4/67c8fb93-02e8-49ef-be93-aa384706b402.jpg", "productUrl": "https://coupa.ng/b4bieV", "categoryName": "완구/취미", "keyword": "완구/취미", "rank": 4, "isRocket": true, "isFreeShipping": false}, {"productId": 4604570174, "productName": "레츠토이 워터슬라이드 유아 DIY 물놀이 목욕놀이 완구, 랜덤발송", "productPrice": 13400, "productImage": "https://static.coupangcdn.com/image/retail/images/1363030391025827-643a272e-c3d9-4690-838d-308f28ce5036.jpg", "productUrl": "https://coupa.ng/b4bieW", "categoryName": "완구/취미", "keyword": "완구/취미", "rank": 5, "isRocket": true, "isFreeShipping": false}, {"productId": 1516258981, "productName": "애들랜드 스피카워터건 물총 2p, 퍼플", "productPrice": 10750, "productImage": "https://static.coupangcdn.com/image/retail/images/2020/04/22/19/2/eb27a055-5989-486c-ab35-12e0ba93b81a.jpg", "productUrl": "https://coupa.ng/b4bieX", "categoryName": "완구/취미", "keyword": "완구/취미", "rank": 6, "isRocket": true, "isFreeShipping": false}, {"productId": 1551133458, "productName": "베스트웨이 고급사각 물놀이 에어 풀장 BW 54005, 혼합색상", "productPrice": 34700, "productImage": "https://static.coupangcdn.com/image/retail/images/652280915549388-6c380efd-e41c-4196-a0aa-027b6696b6d0.jpg", "productUrl": "https://coupa.ng/b4bieY", "categoryName": "완구/취미", "keyword": "완구/취미", "rank": 7, "isRocket": false, "isFreeShipping": true}, {"productId": 1494649567, "productName": "케이에스몰 써니워터 투명 파도타기 튜브 (레드) 스노쿨링 물놀이보트 물놀이튜브 키즈튜브 라운지튜브 어린이튜브 풀장튜브, 레드", "productPrice": 11900, "productImage": "https://static.coupangcdn.com/image/vendor_inventory/images/2019/06/05/18/6/5da734e1-8e91-4b06-a1f5-4e429ecfa4ad.jpg", "productUrl": "https://coupa.ng/b4bie0", "categoryName": "완구/취미", "keyword": "완구/취미", "rank": 8, "isRocket": false, "isFreeShipping": true}, {"productId": 212654666, "productName": "애들랜드 빙글빙글 야자수 낚시놀이세트, 핑크", "productPrice": 12790, "productImage": "https://static.coupangcdn.com/image/retail/images/11676504841682-2ef68a96-a082-445e-968f-e4697337cb39.jpg", "productUrl": "https://coupa.ng/b4bie2", "categoryName": "완구/취미", "keyword": "완구/취미", "rank": 9, "isRocket": true, "isFreeShipping": false}, {"productId": 1551133011, "productName": "베스트웨이 칵테일 캐노피 분수 물놀이 풀장 BW56432, 혼합색상", "productPrice": 139900, "productImage": "https://static.coupangcdn.com/image/retail/images/18983435800073-9a36aef0-eed0-4eb1-9f69-29ca25d9fe4d.jpg", "productUrl": "https://coupa.ng/b4bie3", "categoryName": "완구/취미", "keyword": "완구/취미", "rank": 10, "isRocket": false, "isFreeShipping": true}]}