{"title": "홈인테리어", "item_list": [{"productId": 319688139, "productName": "탐사 포켓용 핫팩 90g, 30개입", "productPrice": 11590, "productImage": "https://static.coupangcdn.com/image/retail/images/14761008202509-1090bc7c-944b-4ece-b81d-1558087e18c4.jpg", "productUrl": "https://link.coupang.com/a/jsiOL", "categoryName": "홈인테리어", "keyword": "홈인테리어", "rank": 1, "isRocket": true, "isFreeShipping": false}, {"productId": 9255652, "productName": "써지오 스위치 개별 멀티탭 4구 DH-2049-MT + 안전커버 2개, 1.5m, 1개", "productPrice": 7760, "productImage": "https://static.coupangcdn.com/image/retail/images/248643851675020-a84be846-7707-42e9-a674-24ae873566f2.jpg", "productUrl": "https://link.coupang.com/a/jsiOM", "categoryName": "홈인테리어", "keyword": "홈인테리어", "rank": 2, "isRocket": true, "isFreeShipping": false}, {"productId": 555006, "productName": "하루온 핫팩 붙이는 타입 50g, 50개입", "productPrice": 19110, "productImage": "https://static.coupangcdn.com/image/retail/images/2019/08/30/15/8/a4502b3c-09d7-4a38-9a47-cc8b05fc3fc1.jpg", "productUrl": "https://link.coupang.com/a/jsiON", "categoryName": "홈인테리어", "keyword": "홈인테리어", "rank": 3, "isRocket": false, "isFreeShipping": true}, {"productId": 327325200, "productName": "쿤달 퍼퓸 디퓨저 200ml 3개 + 섬유스틱 15개 세트, 블랙체리향, 1세트", "productPrice": 18990, "productImage": "https://static.coupangcdn.com/image/retail/images/10657600374477799-8c613631-a2b4-4e6f-9be2-ec3bca8ef1b3.jpg", "productUrl": "https://link.coupang.com/a/jsiOO", "categoryName": "홈인테리어", "keyword": "홈인테리어", "rank": 4, "isRocket": true, "isFreeShipping": false}, {"productId": 1747683800, "productName": "한일의료기 북극곰 전기요, 그레이, 라지(135 x 180 cm)", "productPrice": 30500, "productImage": "https://static.coupangcdn.com/image/retail/images/97318835271380-60267dae-9074-43a4-a345-d3782d1365f9.jpg", "productUrl": "https://link.coupang.com/a/jsiOP", "categoryName": "홈인테리어", "keyword": "홈인테리어", "rank": 5, "isRocket": true, "isFreeShipping": false}, {"productId": 239855078, "productName": "아토젯 필터샤워기 + 헤드필터 3p + 바디필터 3p 세트, 1세트", "productPrice": 29800, "productImage": "https://static.coupangcdn.com/image/vendor_inventory/e4d6/94f87f85076954eef89fdb1bf6554691e6136822173feac8ca84648c7f45.jpg", "productUrl": "https://link.coupang.com/a/jsiOR", "categoryName": "홈인테리어", "keyword": "홈인테리어", "rank": 6, "isRocket": false, "isFreeShipping": true}, {"productId": 44892988, "productName": "쏘핫 붙이는 핫팩 일반 40g, 100개입", "productPrice": 13900, "productImage": "https://static.coupangcdn.com/image/vendor_inventory/d70e/7dff9479641727d74bb47ef86d1b1d74b0cddbaa102a953217d10b3c97b8.jpg", "productUrl": "https://link.coupang.com/a/jsiOS", "categoryName": "홈인테리어", "keyword": "홈인테리어", "rank": 7, "isRocket": true, "isFreeShipping": false}, {"productId": 256738242, "productName": "코멧 코팅 논슬립 옷걸이, 그레이, 30개", "productPrice": 11990, "productImage": "https://static.coupangcdn.com/image/retail/images/267809595247282-58d1ce25-298c-4ef7-bc91-5f870412941d.jpg", "productUrl": "https://link.coupang.com/a/jsiOT", "categoryName": "홈인테리어", "keyword": "홈인테리어", "rank": 8, "isRocket": true, "isFreeShipping": false}, {"productId": 48154062, "productName": "코튼클라우드 호텔수건 200g 40수 코마사, 그레이, 10장", "productPrice": 37400, "productImage": "https://static.coupangcdn.com/image/retail/images/75127176213018-0369195a-3d58-49d9-b11f-3d5aa22ce776.jpg", "productUrl": "https://link.coupang.com/a/jsiOU", "categoryName": "홈인테리어", "keyword": "홈인테리어", "rank": 9, "isRocket": true, "isFreeShipping": false}, {"productId": 19136228, "productName": "써지오 스위치 개별 멀티탭 3구 + 안전커버 DH-2039-RT, 3m, 1세트", "productPrice": 8700, "productImage": "https://static.coupangcdn.com/image/retail/images/249781210469263-0417de88-a01f-486b-bfdc-fc82b7af470d.jpg", "productUrl": "https://link.coupang.com/a/jsiOV", "categoryName": "홈인테리어", "keyword": "홈인테리어", "rank": 10, "isRocket": true, "isFreeShipping": false}]}